mv_platform_core/__init__.py
mv_platform_core/default.py
mv_platform_core/template.py
mv_platform_core/conversion/__init__.py
mv_platform_core/conversion/base.py
mv_platform_core/readers/__init__.py
mv_platform_core/readers/base.py
mv_platform_core/readers/bronze.py
mv_platform_core/writers/__init__.py
mv_platform_core/writers/base.py
mv_platform_core/writers/silver.py
mv_platform_core-0.1.2.dist-info/METADATA
mv_platform_core-0.1.2.dist-info/WHEEL
mv_platform_core-0.1.2.dist-info/RECORD
