Metadata-Version: 2.4
Name: mv-platform-core
Version: 0.1.2
Summary: Add your description here
Requires-Python: >=3.10
Requires-Dist: delta-spark>=3.3.0
Requires-Dist: pydantic>=2.10.6
Requires-Dist: pyspark>=3.5.4
